choumine_math/__init__.py
choumine_math/__main__.py
choumine_math/server.py
choumine_math-0.1.0.dist-info/METADATA
choumine_math-0.1.0.dist-info/WHEEL
choumine_math-0.1.0.dist-info/entry_points.txt
choumine_math-0.1.0.dist-info/RECORD
