Metadata-Version: 2.4
Name: choumine-math
Version: 0.1.0
Summary: Add your description here
Author-email: choumine <569908115@qq.com>
Requires-Python: >=3.13
Requires-Dist: mcp[cli]>=1.6.0
